instanet/__init__.py
instanet/bs_settings.py
instanet/insta_core.py
instanet/insta_network.py
instanet-0.0.4.dist-info/LICENSE.txt
instanet-0.0.4.dist-info/METADATA
instanet-0.0.4.dist-info/WHEEL
instanet-0.0.4.dist-info/top_level.txt
instanet-0.0.4.dist-info/RECORD
