Metadata-Version: 2.1
Name: instanet
Version: 0.0.4
Summary: A python package for analysing Instagram network
Home-page: https://github.com/behrouzz/instanet
Author: Behrouz Safari
Author-email: behrouz.safari@gmail.com
License: MIT
Platform: UNKNOWN
Classifier: Programming Language :: Python :: 3
Classifier: License :: OSI Approved :: MIT License
Classifier: Operating System :: OS Independent
Requires-Python: >=3.4
License-File: LICENSE.txt
Requires-Dist: requests
Requires-Dist: networkx
Requires-Dist: matplotlib
